whatis/__init__.py
whatis/app.py
whatis/config.py
whatis/constants.py
whatis/manage.py
whatis/models.py
whatis/proxies.py
whatis/migrations/README
whatis/migrations/alembic.ini
whatis/migrations/env.py
whatis/migrations/script.py.mako
whatis/migrations/versions/02809806f723_create_tables.py
whatis/routes/__init__.py
whatis/routes/actions.py
whatis/routes/block_action_handlers.py
whatis/routes/dialog_handlers.py
whatis/routes/slack_route.py
whatis/tests/__init__.py
whatis/tests/test_application.py
whatis/utils/__init__.py
whatis/utils/dialog_components.py
whatis/utils/interaction_handler.py
whatis/utils/lookups.py
whatis/utils/message_components.py
whatis/utils/request.py
whatis/utils/responder.py
whatis_bot-1.0.4.data/scripts/whatis-serve
whatis_bot-1.0.4.dist-info/LICENSE
whatis_bot-1.0.4.dist-info/METADATA
whatis_bot-1.0.4.dist-info/WHEEL
whatis_bot-1.0.4.dist-info/top_level.txt
whatis_bot-1.0.4.dist-info/RECORD
